Metadata-Version: 2.1
Name: tgext.rq
Version: 0.0.7
Summary: UNKNOWN
Home-page: https://github.com/eureciclo/tgext.rq
Author: Leonardo Baptista
Author-email: leonardoobaptistaa@gmail.com
License: MIT
Keywords: turbogears2.extension
Platform: UNKNOWN
Classifier: Development Status :: 5 - Production/Stable
Classifier: Framework :: TurboGears
